artifax/__init__.py
artifax/builder.py
artifax/exceptions.py
artifax/models.py
artifax/utils.py
artifax-0.5.dist-info/LICENSE
artifax-0.5.dist-info/METADATA
artifax-0.5.dist-info/WHEEL
artifax-0.5.dist-info/top_level.txt
artifax-0.5.dist-info/RECORD
