Metadata-Version: 2.1
Name: artifax
Version: 0.5
Summary: python package for building artifacts from a computational graph
Home-page: https://github.com/brunolange/artifax
Author: Bruno Lange
Author-email: blangeram@gmail.com
License: UNKNOWN
Platform: UNKNOWN
Requires-Python: >=3.5
License-File: LICENSE
Requires-Dist: pathos
Requires-Dist: exos
Provides-Extra: dev
Requires-Dist: pylint ; extra == 'dev'
